{
  "chunk_metadata": {
    "domain": "public",
    "CIK": "92230",
    "data_type": "SEC",
    "ticker": "TFC",
    "chunk_name": "Other Assets",
    "chunk_id": "other_assets",
    "company_name": "TRUIST FINANCIAL CORPORATION",
    "extraction_date": "2025-09-30T11:01:44.273794",
    "metrics_count": 80,
    "total_company_metrics": 0,
    "chunking_strategy": "context_aware_balanced"
  },
  "metrics": {
    "AccumulatedDepreciationDepletionAndAmortizationPropertyPlantAndEquipment": {
      "taxonomy": "us-gaap",
      "label": "Accumulated Depreciation, Depletion and Amortization, Property, Plant, and Equipment",
      "description": "Amount of accumulated depreciation, depletion and amortization for physical assets used in the normal conduct of business to produce goods and services.",
      "available_units": [
        "USD"
      ],
      "data_points_count": 34,
      "latest_value": {
        "value": 2644000000,
        "date": "2024-12-31",
        "fiscal_year": 2024,
        "form": "10-K",
        "filed": "2025-02-25",
        "unit": "USD",
        "type": "annual"
      },
      "date_range": {
        "earliest": "2009-12-31",
        "latest": "2024-12-31"
      }
    },
    "Assets": {
      "taxonomy": "us-gaap",
      "label": "Assets",
      "description": "Sum of the carrying amounts as of the balance sheet date of all assets that are recognized. Assets are probable future economic benefits obtained or controlled by an entity as a result of past transactions or events.",
      "available_units": [
        "USD"
      ],
      "data_points_count": 141,
      "latest_value": {
        "value": 531176000000,
        "date": "2024-12-31",
        "fiscal_year": 2024,
        "form": "10-K",
        "filed": "2025-02-25",
        "unit": "USD",
        "type": "annual"
      },
      "date_range": {
        "earliest": "2008-12-31",
        "latest": "2025-06-30"
      }
    },
    "AssetsFairValueDisclosure": {
      "taxonomy": "us-gaap",
      "label": "Assets, Fair Value Disclosure",
      "description": "Fair value portion of probable future economic benefits obtained or controlled by an entity as a result of past transactions or events.",
      "available_units": [
        "USD"
      ],
      "data_points_count": 118,
      "latest_value": {
        "value": 78789000000,
        "date": "2024-12-31",
        "fiscal_year": 2024,
        "form": "10-K",
        "filed": "2025-02-25",
        "unit": "USD",
        "type": "annual"
      },
      "date_range": {
        "earliest": "2010-12-31",
        "latest": "2025-06-30"
      }
    },
    "BusinessCombinationRecognizedIdentifiableAssetsAcquiredGoodwillAndLiabilitiesAssumedNet": {
      "taxonomy": "us-gaap",
      "label": "Business Combination, Recognized Identifiable Assets Acquired, Goodwill, and Liabilities Assumed, Net",
      "description": "Amount recognized for assets, including goodwill, in excess of (less than) the aggregate liabilities assumed.",
      "available_units": [
        "USD"
      ],
      "data_points_count": 4,
      "latest_value": {
        "value": 19226000000,
        "date": "2019-12-06",
        "fiscal_year": 2019,
        "form": "10-K",
        "filed": "2020-03-03",
        "unit": "USD",
        "type": "annual"
      },
      "date_range": {
        "earliest": "2019-12-06",
        "latest": "2019-12-06"
      }
    },
    "CapitalLeasedAssetsGross": {
      "taxonomy": "us-gaap",
      "label": "Capital Leased Assets, Gross",
      "description": "Amount before accumulated depreciation of leased physical assets used in the normal conduct of business to produce goods and services.",
      "available_units": [
        "USD"
      ],
      "data_points_count": 10,
      "latest_value": {
        "value": 67000000,
        "date": "2015-12-31",
        "fiscal_year": 2015,
        "form": "10-K",
        "filed": "2016-02-25",
        "unit": "USD",
        "type": "annual"
      },
      "date_range": {
        "earliest": "2010-12-31",
        "latest": "2015-12-31"
      }
    },
    "DeferredTaxAssetsGross": {
      "taxonomy": "us-gaap",
      "label": "Deferred Tax Assets, Gross",
      "description": "Amount before allocation of valuation allowances of deferred tax asset attributable to deductible temporary differences and carryforwards.",
      "available_units": [
        "USD"
      ],
      "data_points_count": 22,
      "latest_value": {
        "value": 5523000000,
        "date": "2024-12-31",
        "fiscal_year": 2024,
        "form": "10-K",
        "filed": "2025-02-25",
        "unit": "USD",
        "type": "annual"
      },
      "date_range": {
        "earliest": "2015-12-31",
        "latest": "2024-12-31"
      }
    },
    "DeferredTaxAssetsHedgingTransactions": {
      "taxonomy": "us-gaap",
      "label": "Deferred Tax Assets, Hedging Transactions",
      "description": "Amount before allocation of valuation allowances of deferred tax asset attributable to deductible temporary differences from hedging transactions.",
      "available_units": [
        "USD"
      ],
      "data_points_count": 6,
      "latest_value": {
        "value": 0,
        "date": "2013-12-31",
        "fiscal_year": 2013,
        "form": "10-K",
        "filed": "2014-02-26",
        "unit": "USD",
        "type": "annual"
      },
      "date_range": {
        "earliest": "2010-12-31",
        "latest": "2013-12-31"
      }
    },
    "DeferredTaxAssetsNet": {
      "taxonomy": "us-gaap",
      "label": "Deferred Tax Assets, Net of Valuation Allowance",
      "description": "Amount after allocation of valuation allowances of deferred tax asset attributable to deductible temporary differences and carryforwards.",
      "available_units": [
        "USD"
      ],
      "data_points_count": 16,
      "latest_value": {
        "value": 5419000000,
        "date": "2024-12-31",
        "fiscal_year": 2024,
        "form": "10-K",
        "filed": "2025-02-25",
        "unit": "USD",
        "type": "annual"
      },
      "date_range": {
        "earliest": "2009-12-31",
        "latest": "2024-12-31"
      }
    },
    "DeferredTaxAssetsOperatingLossCarryforwards": {
      "taxonomy": "us-gaap",
      "label": "Deferred Tax Assets, Operating Loss Carryforwards",
      "description": "Amount before allocation of valuation allowances of deferred tax asset attributable to deductible operating loss carryforwards.",
      "available_units": [
        "USD"
      ],
      "data_points_count": 14,
      "latest_value": {
        "value": 163000000,
        "date": "2024-12-31",
        "fiscal_year": 2024,
        "form": "10-K",
        "filed": "2025-02-25",
        "unit": "USD",
        "type": "annual"
      },
      "date_range": {
        "earliest": "2018-12-31",
        "latest": "2024-12-31"
      }
    },
    "DeferredTaxAssetsOtherComprehensiveLoss": {
      "taxonomy": "us-gaap",
      "label": "Deferred Tax Assets, Other Comprehensive Loss",
      "description": "Amount before allocation of valuation allowances of deferred tax asset attributable to deductible temporary differences from unrealized losses in other comprehensive income.",
      "available_units": [
        "USD"
      ],
      "data_points_count": 30,
      "latest_value": {
        "value": 2541000000,
        "date": "2024-12-31",
        "fiscal_year": 2024,
        "form": "10-K",
        "filed": "2025-02-25",
        "unit": "USD",
        "type": "annual"
      },
      "date_range": {
        "earliest": "2008-12-31",
        "latest": "2024-12-31"
      }
    },
    "DeferredTaxAssetsTaxDeferredExpense": {
      "taxonomy": "us-gaap",
      "label": "Deferred Tax Assets, Tax Deferred Expense",
      "description": "Amount, before allocation of valuation allowances, of deferred tax asset attributable to deductible differences from reserves and accruals, compensation and benefit costs, and other provisions, reserves, and allowances.",
      "available_units": [
        "USD"
      ],
      "data_points_count": 10,
      "latest_value": {
        "value": 1894000000,
        "date": "2015-12-31",
        "fiscal_year": 2015,
        "form": "10-K",
        "filed": "2016-02-25",
        "unit": "USD",
        "type": "annual"
      },
      "date_range": {
        "earliest": "2010-12-31",
        "latest": "2015-12-31"
      }
    },
    "DeferredTaxAssetsTaxDeferredExpenseCompensationAndBenefitsPostretirementBenefits": {
      "taxonomy": "us-gaap",
      "label": "Deferred Tax Assets, Tax Deferred Expense, Compensation and Benefits, Postretirement Benefits",
      "description": "Amount before allocation of valuation allowances of deferred tax asset attributable to deductible temporary differences from postretirement benefits.",
      "available_units": [
        "USD"
      ],
      "data_points_count": 32,
      "latest_value": {
        "value": 705000000,
        "date": "2024-12-31",
        "fiscal_year": 2024,
        "form": "10-K",
        "filed": "2025-02-25",
        "unit": "USD",
        "type": "annual"
      },
      "date_range": {
        "earliest": "2010-12-31",
        "latest": "2024-12-31"
      }
    },
    "DeferredTaxAssetsTaxDeferredExpenseCompensationAndBenefitsShareBasedCompensationCost": {
      "taxonomy": "us-gaap",
      "label": "Deferred Tax Assets, Tax Deferred Expense, Compensation and Benefits, Share-based Compensation Cost",
      "description": "Amount before allocation of valuation allowances of deferred tax asset attributable to deductible temporary differences from share-based compensation.",
      "available_units": [
        "USD"
      ],
      "data_points_count": 18,
      "latest_value": {
        "value": 82000000,
        "date": "2018-12-31",
        "fiscal_year": 2018,
        "form": "10-K",
        "filed": "2019-02-26",
        "unit": "USD",
        "type": "annual"
      },
      "date_range": {
        "earliest": "2010-12-31",
        "latest": "2018-12-31"
      }
    },
    "DeferredTaxAssetsTaxDeferredExpenseOther": {
      "taxonomy": "us-gaap",
      "label": "Deferred Tax Assets, Tax Deferred Expense, Other",
      "description": "Amount, before allocation of valuation allowance, of deferred tax asset attributable to deductible temporary differences from provisions, reserves, allowances, and accruals, classified as other.",
      "available_units": [
        "USD"
      ],
      "data_points_count": 32,
      "latest_value": {
        "value": 15000000,
        "date": "2024-12-31",
        "fiscal_year": 2024,
        "form": "10-K",
        "filed": "2025-02-25",
        "unit": "USD",
        "type": "annual"
      },
      "date_range": {
        "earliest": "2010-12-31",
        "latest": "2024-12-31"
      }
    },
    "DeferredTaxAssetsTaxDeferredExpenseReservesAndAccrualsOther": {
      "taxonomy": "us-gaap",
      "label": "Deferred Tax Assets, Tax Deferred Expense, Reserves and Accruals, Other",
      "description": "Amount, before allocation of valuation allowance, of deferred tax asset attributable to deductible temporary differences from reserves and accruals, classified as other.",
      "available_units": [
        "USD"
      ],
      "data_points_count": 24,
      "latest_value": {
        "value": 265000000,
        "date": "2024-12-31",
        "fiscal_year": 2024,
        "form": "10-K",
        "filed": "2025-02-25",
        "unit": "USD",
        "type": "annual"
      },
      "date_range": {
        "earliest": "2014-12-31",
        "latest": "2024-12-31"
      }
    },
    "DeferredTaxAssetsValuationAllowance": {
      "taxonomy": "us-gaap",
      "label": "Deferred Tax Assets, Valuation Allowance",
      "description": "Amount of deferred tax assets for which it is more likely than not that a tax benefit will not be realized.",
      "available_units": [
        "USD"
      ],
      "data_points_count": 14,
      "latest_value": {
        "value": 104000000,
        "date": "2024-12-31",
        "fiscal_year": 2024,
        "form": "10-K",
        "filed": "2025-02-25",
        "unit": "USD",
        "type": "annual"
      },
      "date_range": {
        "earliest": "2018-12-31",
        "latest": "2024-12-31"
      }
    },
    "DeferredTaxLiabilitiesPrepaidExpenses": {
      "taxonomy": "us-gaap",
      "label": "Deferred Tax Liabilities, Prepaid Expenses",
      "description": "Amount of deferred tax consequences attributable to taxable temporary differences derived from prepaid expenses.",
      "available_units": [
        "USD"
      ],
      "data_points_count": 18,
      "latest_value": {
        "value": 1914000000,
        "date": "2024-12-31",
        "fiscal_year": 2024,
        "form": "10-K",
        "filed": "2025-02-25",
        "unit": "USD",
        "type": "annual"
      },
      "date_range": {
        "earliest": "2016-12-31",
        "latest": "2024-12-31"
      }
    },
    "DeferredTaxLiabilitiesPrepaidPensionCosts": {
      "taxonomy": "us-gaap",
      "label": "Deferred Tax Liabilities, Prepaid Pension Costs (Deprecated 2013-01-31)",
      "description": "The amount as of the balance sheet date of the estimated future tax effects attributable to the difference between the tax basis of pension liabilities funded in advance and the basis of a prepaid pension asset determined in accordance with generally accepted accounting principles. The difference in basis of such costs will increase future taxable income when such basis difference reverses. Prepaid pension costs represented the cumulative employer's contributions in excess of net pension cost recognized, before the adoption of the recognition provisions of FAS 158. Under FAS 158, prepaid pension costs are no longer recognized in the statement of financial position.",
      "available_units": [
        "USD"
      ],
      "data_points_count": 6,
      "latest_value": {
        "value": 431000000,
        "date": "2013-12-31",
        "fiscal_year": 2013,
        "form": "10-K",
        "filed": "2014-02-26",
        "unit": "USD",
        "type": "annual"
      },
      "date_range": {
        "earliest": "2010-12-31",
        "latest": "2013-12-31"
      }
    },
    "DefinedBenefitPlanAssumptionsUsedCalculatingNetPeriodicBenefitCostExpectedLongTermReturnOnAssets": {
      "taxonomy": "us-gaap",
      "label": "Defined Benefit Plan, Assumptions Used Calculating Net Periodic Benefit Cost, Expected Long-term Rate of Return on Plan Assets",
      "description": "Weighted average rate of return on plan assets, reflecting average rate of earnings expected on existing plan assets and expected contributions, used to determine net periodic benefit cost of defined benefit plan.",
      "available_units": [
        "pure"
      ],
      "data_points_count": 46,
      "latest_value": {
        "value": 0.068,
        "date": "2024-12-31",
        "fiscal_year": 2024,
        "form": "10-K",
        "filed": "2025-02-25",
        "unit": "pure",
        "type": "annual"
      },
      "date_range": {
        "earliest": "2009-12-31",
        "latest": "2024-12-31"
      }
    },
    "DepreciationNonproduction": {
      "taxonomy": "us-gaap",
      "label": "Depreciation, Nonproduction",
      "description": "The expense recognized in the current period that allocates the cost of nonproduction tangible assets over their useful lives.",
      "available_units": [
        "USD"
      ],
      "data_points_count": 134,
      "latest_value": {
        "value": 613000000,
        "date": "2024-12-31",
        "fiscal_year": 2024,
        "form": "10-K",
        "filed": "2025-02-25",
        "unit": "USD",
        "type": "annual"
      },
      "date_range": {
        "earliest": "2009-12-31",
        "latest": "2025-06-30"
      }
    },
    "DepreciationPremisesAndEquipment": {
      "taxonomy": "us-gaap",
      "label": "Depreciation Premises and Equipment (Deprecated 2011-01-31)",
      "description": "The amount of expense charged against earnings in the period to allocate the cost, net of salvage value, of premises and equipment over their remaining estimated productive lives.",
      "available_units": [
        "USD"
      ],
      "data_points_count": 18,
      "latest_value": {
        "value": 260000000,
        "date": "2010-12-31",
        "fiscal_year": 2010,
        "form": "10-K",
        "filed": "2011-02-25",
        "unit": "USD",
        "type": "annual"
      },
      "date_range": {
        "earliest": "2007-12-31",
        "latest": "2011-03-31"
      }
    },
    "DerivativeAssetFairValueGrossAssetIncludingNotSubjectToMasterNettingArrangement": {
      "taxonomy": "us-gaap",
      "label": "Derivative Asset, Fair Value, Gross Asset Including Not Subject to Master Netting Arrangement",
      "description": "Fair value, before effects of master netting arrangements, of a financial asset or other contract with one or more underlyings, notional amount or payment provision or both, and the contract can be net settled by means outside the contract or delivery of an asset. Includes assets not subject to a master netting arrangement and elected not to be offset.",
      "available_units": [
        "USD"
      ],
      "data_points_count": 52,
      "latest_value": {
        "value": 2824000000,
        "date": "2024-12-31",
        "fiscal_year": 2024,
        "form": "10-K",
        "filed": "2025-02-25",
        "unit": "USD",
        "type": "annual"
      },
      "date_range": {
        "earliest": "2018-12-31",
        "latest": "2025-06-30"
      }
    },
    "DerivativeAssetFairValueOffsetAgainstCollateralNetOfNotSubjectToMasterNettingArrangementPolicyElection": {
      "taxonomy": "us-gaap",
      "label": "Derivative Asset, Fair Value, Offset Against Collateral, Net of Not Subject to Master Netting Arrangement, Policy Election",
      "description": "Fair value, after effects of master netting arrangements, deduction of assets not subject to a master netting arrangement and elected not to be offset, of financial asset or other contract with one or more underlyings, notional amount or payment provision or both, and the contract can be net settled by means outside the contract or delivery of an asset, offset against an obligation to return collateral.",
      "available_units": [
        "USD"
      ],
      "data_points_count": 22,
      "latest_value": {
        "value": 146000000,
        "date": "2018-12-31",
        "fiscal_year": 2018,
        "form": "10-K",
        "filed": "2019-02-26",
        "unit": "USD",
        "type": "annual"
      },
      "date_range": {
        "earliest": "2015-12-31",
        "latest": "2019-03-31"
      }
    },
    "DerivativeAssetNotOffsetPolicyElectionDeduction": {
      "taxonomy": "us-gaap",
      "label": "Derivative Asset, Not Offset, Policy Election Deduction",
      "description": "Fair value of financial asset or other contract with one or more underlyings, notional amount or payment provision or both, and the contract can be net settled by means outside the contract or delivery of an asset, elected not to be offset, deducted from derivative assets.",
      "available_units": [
        "USD"
      ],
      "data_points_count": 25,
      "latest_value": {
        "value": 47000000,
        "date": "2018-12-31",
        "fiscal_year": 2019,
        "form": "10-K",
        "filed": "2020-03-03",
        "unit": "USD",
        "type": "annual"
      },
      "date_range": {
        "earliest": "2015-12-31",
        "latest": "2019-03-31"
      }
    },
    "DerivativeAssetNotSubjectToMasterNettingArrangement": {
      "taxonomy": "us-gaap",
      "label": "Derivative Asset, Not Subject to Master Netting Arrangement",
      "description": "Fair value of financial asset or other contract with one or more underlyings, notional amount or payment provision or both, and the contract can be net settled by means outside the contract or delivery of an asset, not subject to a master netting arrangement.",
      "available_units": [
        "USD"
      ],
      "data_points_count": 4,
      "latest_value": {
        "value": 679000000,
        "date": "2019-09-30",
        "fiscal_year": 2019,
        "fiscal_period": "Q3",
        "form": "10-Q",
        "filed": "2019-10-25",
        "unit": "USD",
        "type": "quarterly"
      },
      "date_range": {
        "earliest": "2018-12-31",
        "latest": "2019-09-30"
      }
    },
    "DerivativeAssets": {
      "taxonomy": "us-gaap",
      "label": "Derivative Asset",
      "description": "Fair value, after the effects of master netting arrangements, of a financial asset or other contract with one or more underlyings, notional amount or payment provision or both, and the contract can be net settled by means outside the contract or delivery of an asset. Includes assets not subject to a master netting arrangement and not elected to be offset.",
      "available_units": [
        "USD"
      ],
      "data_points_count": 52,
      "latest_value": {
        "value": 966000000,
        "date": "2024-12-31",
        "fiscal_year": 2024,
        "form": "10-K",
        "filed": "2025-02-25",
        "unit": "USD",
        "type": "annual"
      },
      "date_range": {
        "earliest": "2018-12-31",
        "latest": "2025-06-30"
      }
    },
    "DerivativeFairValueOfDerivativeAsset": {
      "taxonomy": "us-gaap",
      "label": "Derivative Asset, Fair Value, Gross Asset",
      "description": "Fair value, before effects of master netting arrangements, of a financial asset or other contract with one or more underlyings, notional amount or payment provision or both, and the contract can be net settled by means outside the contract or delivery of an asset. Includes assets elected not to be offset. Excludes assets not subject to a master netting arrangement.",
      "available_units": [
        "USD"
      ],
      "data_points_count": 74,
      "latest_value": {
        "value": 246000000,
        "date": "2018-12-31",
        "fiscal_year": 2018,
        "form": "10-K",
        "filed": "2019-02-26",
        "unit": "USD",
        "type": "annual"
      },
      "date_range": {
        "earliest": "2009-12-31",
        "latest": "2019-03-31"
      }
    },
    "DerivativeFairValueOfDerivativeNet": {
      "taxonomy": "us-gaap",
      "label": "Derivative, Fair Value, Net",
      "description": "Fair value of the assets less the liabilities of a derivative or group of derivatives.",
      "available_units": [
        "USD"
      ],
      "data_points_count": 4,
      "latest_value": {
        "value": 277000000,
        "date": "2010-09-30",
        "fiscal_year": 2010,
        "fiscal_period": "Q3",
        "form": "10-Q",
        "filed": "2010-11-09",
        "unit": "USD",
        "type": "quarterly"
      },
      "date_range": {
        "earliest": "2009-12-31",
        "latest": "2010-09-30"
      }
    },
    "EquipmentExpense": {
      "taxonomy": "us-gaap",
      "label": "Equipment Expense",
      "description": "This element represents equipment expense including depreciation, repairs, rentals, and service contract costs. This item also includes equipment purchases which do not qualify for capitalization in accordance with the entity's accounting policy. This item may also include furniture expenses.",
      "available_units": [
        "USD"
      ],
      "data_points_count": 77,
      "latest_value": {
        "value": 373000000,
        "date": "2024-12-31",
        "fiscal_year": 2024,
        "form": "10-K",
        "filed": "2025-02-25",
        "unit": "USD",
        "type": "annual"
      },
      "date_range": {
        "earliest": "2017-12-31",
        "latest": "2025-06-30"
      }
    },
    "FinanceLeaseRightOfUseAsset": {
      "taxonomy": "us-gaap",
      "label": "Finance Lease, Right-of-Use Asset, after Accumulated Amortization",
      "description": "Amount, after accumulated amortization, of right-of-use asset from finance lease.",
      "available_units": [
        "USD"
      ],
      "data_points_count": 26,
      "latest_value": {
        "value": 36000000,
        "date": "2020-12-31",
        "fiscal_year": 2020,
        "form": "10-K",
        "filed": "2021-02-24",
        "unit": "USD",
        "type": "annual"
      },
      "date_range": {
        "earliest": "2019-03-31",
        "latest": "2025-06-30"
      }
    },
    "FiniteLivedIntangibleAssetsAccumulatedAmortization": {
      "taxonomy": "us-gaap",
      "label": "Finite-Lived Intangible Assets, Accumulated Amortization",
      "description": "Accumulated amount of amortization of assets, excluding financial assets and goodwill, lacking physical substance with a finite life.",
      "available_units": [
        "USD"
      ],
      "data_points_count": 118,
      "latest_value": {
        "value": 2361000000,
        "date": "2024-12-31",
        "fiscal_year": 2024,
        "form": "10-K",
        "filed": "2025-02-25",
        "unit": "USD",
        "type": "annual"
      },
      "date_range": {
        "earliest": "2009-12-31",
        "latest": "2025-06-30"
      }
    },
    "FiniteLivedIntangibleAssetsAmortizationExpense": {
      "taxonomy": "us-gaap",
      "label": "Finite-Lived Intangible Assets, Amortization Expense (Deprecated 2012-01-31)",
      "description": "Aggregate amount of intangible asset amortization recognized as expense during the period.",
      "available_units": [
        "USD"
      ],
      "data_points_count": 6,
      "latest_value": {
        "value": 99000000,
        "date": "2011-12-31",
        "fiscal_year": 2011,
        "form": "10-K",
        "filed": "2012-02-27",
        "unit": "USD",
        "type": "annual"
      },
      "date_range": {
        "earliest": "2008-12-31",
        "latest": "2011-12-31"
      }
    },
    "FiniteLivedIntangibleAssetsAmortizationExpenseAfterYearFive": {
      "taxonomy": "us-gaap",
      "label": "Finite-Lived Intangible Asset, Expected Amortization, after Year Five",
      "description": "Amount of amortization for asset, excluding financial asset and goodwill, lacking physical substance with finite life expected to be recognized after fifth fiscal year following current fiscal year. Excludes interim and annual periods when interim periods are reported from current statement of financial position date (rolling approach).",
      "available_units": [
        "USD"
      ],
      "data_points_count": 7,
      "latest_value": {
        "value": 416000000,
        "date": "2024-12-31",
        "fiscal_year": 2024,
        "form": "10-K",
        "filed": "2025-02-25",
        "unit": "USD",
        "type": "annual"
      },
      "date_range": {
        "earliest": "2019-12-31",
        "latest": "2024-12-31"
      }
    },
    "FiniteLivedIntangibleAssetsAmortizationExpenseNextTwelveMonths": {
      "taxonomy": "us-gaap",
      "label": "Finite-Lived Intangible Asset, Expected Amortization, Year One",
      "description": "Amount of amortization for assets, excluding financial assets and goodwill, lacking physical substance with finite life expected to be recognized in next fiscal year following current fiscal year. Excludes interim and annual periods when interim periods are reported from current statement of financial position date (rolling approach).",
      "available_units": [
        "USD"
      ],
      "data_points_count": 14,
      "latest_value": {
        "value": 292000000,
        "date": "2024-12-31",
        "fiscal_year": 2024,
        "form": "10-K",
        "filed": "2025-02-25",
        "unit": "USD",
        "type": "annual"
      },
      "date_range": {
        "earliest": "2013-12-31",
        "latest": "2024-12-31"
      }
    },
    "FiniteLivedIntangibleAssetsAmortizationExpenseYearFive": {
      "taxonomy": "us-gaap",
      "label": "Finite-Lived Intangible Asset, Expected Amortization, Year Five",
      "description": "Amount of amortization for assets, excluding financial assets and goodwill, lacking physical substance with finite life expected to be recognized in fifth fiscal year following current fiscal year. Excludes interim and annual periods when interim periods are reported from current statement of financial position date (rolling approach).",
      "available_units": [
        "USD"
      ],
      "data_points_count": 14,
      "latest_value": {
        "value": 170000000,
        "date": "2024-12-31",
        "fiscal_year": 2024,
        "form": "10-K",
        "filed": "2025-02-25",
        "unit": "USD",
        "type": "annual"
      },
      "date_range": {
        "earliest": "2013-12-31",
        "latest": "2024-12-31"
      }
    },
    "FiniteLivedIntangibleAssetsAmortizationExpenseYearFour": {
      "taxonomy": "us-gaap",
      "label": "Finite-Lived Intangible Asset, Expected Amortization, Year Four",
      "description": "Amount of amortization for assets, excluding financial assets and goodwill, lacking physical substance with finite life expected to be recognized in fourth fiscal year following current fiscal year. Excludes interim and annual periods when interim periods are reported from current statement of financial position date (rolling approach).",
      "available_units": [
        "USD"
      ],
      "data_points_count": 14,
      "latest_value": {
        "value": 197000000,
        "date": "2024-12-31",
        "fiscal_year": 2024,
        "form": "10-K",
        "filed": "2025-02-25",
        "unit": "USD",
        "type": "annual"
      },
      "date_range": {
        "earliest": "2013-12-31",
        "latest": "2024-12-31"
      }
    },
    "FiniteLivedIntangibleAssetsAmortizationExpenseYearThree": {
      "taxonomy": "us-gaap",
      "label": "Finite-Lived Intangible Asset, Expected Amortization, Year Three",
      "description": "Amount of amortization for assets, excluding financial assets and goodwill, lacking physical substance with finite life expected to be recognized in third fiscal year following current fiscal year. Excludes interim and annual periods when interim periods are reported from current statement of financial position date (rolling approach).",
      "available_units": [
        "USD"
      ],
      "data_points_count": 14,
      "latest_value": {
        "value": 223000000,
        "date": "2024-12-31",
        "fiscal_year": 2024,
        "form": "10-K",
        "filed": "2025-02-25",
        "unit": "USD",
        "type": "annual"
      },
      "date_range": {
        "earliest": "2013-12-31",
        "latest": "2024-12-31"
      }
    },
    "FiniteLivedIntangibleAssetsAmortizationExpenseYearTwo": {
      "taxonomy": "us-gaap",
      "label": "Finite-Lived Intangible Asset, Expected Amortization, Year Two",
      "description": "Amount of amortization for assets, excluding financial assets and goodwill, lacking physical substance with finite life expected to be recognized in second fiscal year following current fiscal year. Excludes interim and annual periods when interim periods are reported from current statement of financial position date (rolling approach).",
      "available_units": [
        "USD"
      ],
      "data_points_count": 14,
      "latest_value": {
        "value": 252000000,
        "date": "2024-12-31",
        "fiscal_year": 2024,
        "form": "10-K",
        "filed": "2025-02-25",
        "unit": "USD",
        "type": "annual"
      },
      "date_range": {
        "earliest": "2013-12-31",
        "latest": "2024-12-31"
      }
    },
    "FiniteLivedIntangibleAssetsGross": {
      "taxonomy": "us-gaap",
      "label": "Finite-Lived Intangible Assets, Gross",
      "description": "Amount before amortization of assets, excluding financial assets and goodwill, lacking physical substance with a finite life.",
      "available_units": [
        "USD"
      ],
      "data_points_count": 118,
      "latest_value": {
        "value": 3911000000,
        "date": "2024-12-31",
        "fiscal_year": 2024,
        "form": "10-K",
        "filed": "2025-02-25",
        "unit": "USD",
        "type": "annual"
      },
      "date_range": {
        "earliest": "2009-12-31",
        "latest": "2025-06-30"
      }
    },
    "FiniteLivedIntangibleAssetsNet": {
      "taxonomy": "us-gaap",
      "label": "Finite-Lived Intangible Assets, Net",
      "description": "Amount after amortization of assets, excluding financial assets and goodwill, lacking physical substance with a finite life.",
      "available_units": [
        "USD"
      ],
      "data_points_count": 126,
      "latest_value": {
        "value": 1550000000,
        "date": "2024-12-31",
        "fiscal_year": 2024,
        "form": "10-K",
        "filed": "2025-02-25",
        "unit": "USD",
        "type": "annual"
      },
      "date_range": {
        "earliest": "2009-12-31",
        "latest": "2025-06-30"
      }
    },
    "ForeclosedRealEstateExpense": {
      "taxonomy": "us-gaap",
      "label": "Foreclosed Real Estate Expense",
      "description": "Amount of expense recognized during the period for the foreclosure on real estate assets.",
      "available_units": [
        "USD"
      ],
      "data_points_count": 99,
      "latest_value": {
        "value": 53000000,
        "date": "2015-12-31",
        "fiscal_year": 2015,
        "form": "10-K",
        "filed": "2016-02-25",
        "unit": "USD",
        "type": "annual"
      },
      "date_range": {
        "earliest": "2007-12-31",
        "latest": "2016-09-30"
      }
    },
    "FurnitureAndFixturesGross": {
      "taxonomy": "us-gaap",
      "label": "Furniture and Fixtures, Gross",
      "description": "Amount before accumulated depreciation of equipment commonly used in offices and stores that have no permanent connection to the structure of a building or utilities. Examples include, but are not limited to, desks, chairs, tables, and bookcases.",
      "available_units": [
        "USD"
      ],
      "data_points_count": 10,
      "latest_value": {
        "value": 1030000000,
        "date": "2015-12-31",
        "fiscal_year": 2015,
        "form": "10-K",
        "filed": "2016-02-25",
        "unit": "USD",
        "type": "annual"
      },
      "date_range": {
        "earliest": "2010-12-31",
        "latest": "2015-12-31"
      }
    },
    "GainLossOnSaleOfOtherAssets": {
      "taxonomy": "us-gaap",
      "label": "Gain (Loss) on Disposition of Other Assets",
      "description": "Amount of gain (loss) on sale or disposal of other assets.",
      "available_units": [
        "USD"
      ],
      "data_points_count": 39,
      "latest_value": {
        "value": -22000000,
        "date": "2014-12-31",
        "fiscal_year": 2014,
        "form": "10-K",
        "filed": "2015-02-25",
        "unit": "USD",
        "type": "annual"
      },
      "date_range": {
        "earliest": "2008-12-31",
        "latest": "2014-12-31"
      }
    },
    "Goodwill": {
      "taxonomy": "us-gaap",
      "label": "Goodwill",
      "description": "Amount after accumulated impairment loss of an asset representing future economic benefits arising from other assets acquired in a business combination that are not individually identified and separately recognized.",
      "available_units": [
        "USD"
      ],
      "data_points_count": 172,
      "latest_value": {
        "value": 17125000000,
        "date": "2024-12-31",
        "fiscal_year": 2024,
        "form": "10-K",
        "filed": "2025-02-25",
        "unit": "USD",
        "type": "annual"
      },
      "date_range": {
        "earliest": "2008-12-31",
        "latest": "2025-06-30"
      }
    },
    "GoodwillAcquiredDuringPeriod": {
      "taxonomy": "us-gaap",
      "label": "Goodwill, Acquired During Period",
      "description": "Amount of increase in asset representing future economic benefits arising from other assets acquired in a business combination that are not individually identified and separately recognized resulting from a business combination.",
      "available_units": [
        "USD"
      ],
      "data_points_count": 59,
      "latest_value": {
        "value": 912000000,
        "date": "2022-12-31",
        "fiscal_year": 2022,
        "form": "10-K",
        "filed": "2023-02-28",
        "unit": "USD",
        "type": "annual"
      },
      "date_range": {
        "earliest": "2009-12-31",
        "latest": "2022-12-31"
      }
    },
    "GoodwillImpairmentLoss": {
      "taxonomy": "us-gaap",
      "label": "Goodwill, Impairment Loss",
      "description": "Amount of loss from the write-down of an asset representing the future economic benefits arising from other assets acquired in a business combination that are not individually identified and separately recognized.",
      "available_units": [
        "USD"
      ],
      "data_points_count": 15,
      "latest_value": {
        "value": 0,
        "date": "2024-12-31",
        "fiscal_year": 2024,
        "form": "10-K",
        "filed": "2025-02-25",
        "unit": "USD",
        "type": "annual"
      },
      "date_range": {
        "earliest": "2011-03-31",
        "latest": "2024-12-31"
      }
    },
    "GoodwillPurchaseAccountingAdjustments": {
      "taxonomy": "us-gaap",
      "label": "Goodwill, Purchase Accounting Adjustments",
      "description": "Amount of increase (decrease) from adjustments after acquisition date under purchase accounting of an asset representing the future economic benefits arising from other assets acquired in a business combination that are not individually identified and separately recognized.",
      "available_units": [
        "USD"
      ],
      "data_points_count": 62,
      "latest_value": {
        "value": 1000000,
        "date": "2024-12-31",
        "fiscal_year": 2024,
        "form": "10-K",
        "filed": "2025-02-25",
        "unit": "USD",
        "type": "annual"
      },
      "date_range": {
        "earliest": "2013-12-31",
        "latest": "2024-12-31"
      }
    },
    "GoodwillTranslationAndPurchaseAccountingAdjustments": {
      "taxonomy": "us-gaap",
      "label": "Goodwill, Translation and Purchase Accounting Adjustments",
      "description": "Amount of increase (decrease) from foreign currency translation adjustments and purchase accounting adjustments of an asset representing future economic benefits arising from other assets acquired in a business combination that are not individually identified and separately recognized.",
      "available_units": [
        "USD"
      ],
      "data_points_count": 19,
      "latest_value": {
        "value": 0,
        "date": "2014-12-31",
        "fiscal_year": 2014,
        "form": "10-K",
        "filed": "2015-02-25",
        "unit": "USD",
        "type": "annual"
      },
      "date_range": {
        "earliest": "2009-12-31",
        "latest": "2014-12-31"
      }
    },
    "GoodwillWrittenOffRelatedToSaleOfBusinessUnit": {
      "taxonomy": "us-gaap",
      "label": "Goodwill, Written off Related to Sale of Business Unit",
      "description": "Amount of divestiture of an asset representing future economic benefits arising from other assets acquired in a business combination that are not individually identified and separately recognized.",
      "available_units": [
        "USD"
      ],
      "data_points_count": 7,
      "latest_value": {
        "value": 32000000,
        "date": "2024-12-31",
        "fiscal_year": 2024,
        "form": "10-K",
        "filed": "2025-02-25",
        "unit": "USD",
        "type": "annual"
      },
      "date_range": {
        "earliest": "2015-12-31",
        "latest": "2024-12-31"
      }
    },
    "IncomeTaxExaminationInterestAccrued": {
      "taxonomy": "us-gaap",
      "label": "Income Tax Examination, Interest Accrued",
      "description": "The amount of estimated interest accrued as of the balance sheet date arising from income tax examinations.",
      "available_units": [
        "USD"
      ],
      "data_points_count": 13,
      "latest_value": {
        "value": 181000000,
        "date": "2015-12-31",
        "fiscal_year": 2015,
        "form": "10-K",
        "filed": "2016-02-25",
        "unit": "USD",
        "type": "annual"
      },
      "date_range": {
        "earliest": "2011-12-31",
        "latest": "2015-12-31"
      }
    },
    "IncomeTaxExaminationPenaltiesAndInterestAccrued": {
      "taxonomy": "us-gaap",
      "label": "Income Tax Examination, Penalties and Interest Accrued",
      "description": "The amount of estimated penalties and interest accrued as of the balance sheet date arising from income tax examinations.",
      "available_units": [
        "USD"
      ],
      "data_points_count": 3,
      "latest_value": {
        "value": 181000000,
        "date": "2015-12-31",
        "fiscal_year": 2016,
        "fiscal_period": "Q3",
        "form": "10-Q",
        "filed": "2016-10-24",
        "unit": "USD",
        "type": "quarterly"
      },
      "date_range": {
        "earliest": "2015-12-31",
        "latest": "2015-12-31"
      }
    },
    "IncreaseDecreaseInDerivativeAssets": {
      "taxonomy": "us-gaap",
      "label": "Increase (Decrease) in Derivative Assets",
      "description": "The increase (decrease) during the period in the carrying value of derivative instruments reported as assets that are due to be disposed of within one year (or the normal operating cycle, if longer).",
      "available_units": [
        "USD"
      ],
      "data_points_count": 48,
      "latest_value": {
        "value": 587000000,
        "date": "2024-12-31",
        "fiscal_year": 2024,
        "form": "10-K",
        "filed": "2025-02-25",
        "unit": "USD",
        "type": "annual"
      },
      "date_range": {
        "earliest": "2018-12-31",
        "latest": "2025-06-30"
      }
    },
    "IncreaseDecreaseInOtherNoncurrentAssets": {
      "taxonomy": "us-gaap",
      "label": "Increase (Decrease) in Other Noncurrent Assets",
      "description": "Amount of increase (decrease) in noncurrent assets classified as other.",
      "available_units": [
        "USD"
      ],
      "data_points_count": 55,
      "latest_value": {
        "value": 675000000,
        "date": "2024-12-31",
        "fiscal_year": 2024,
        "form": "10-K",
        "filed": "2025-02-25",
        "unit": "USD",
        "type": "annual"
      },
      "date_range": {
        "earliest": "2017-12-31",
        "latest": "2025-06-30"
      }
    },
    "IncreaseDecreaseInOtherOperatingAssets": {
      "taxonomy": "us-gaap",
      "label": "Increase (Decrease) in Other Operating Assets",
      "description": "Amount of increase (decrease) in operating assets classified as other.",
      "available_units": [
        "USD"
      ],
      "data_points_count": 77,
      "latest_value": {
        "value": 568000000,
        "date": "2016-12-31",
        "fiscal_year": 2016,
        "form": "10-K",
        "filed": "2017-02-21",
        "unit": "USD",
        "type": "annual"
      },
      "date_range": {
        "earliest": "2007-12-31",
        "latest": "2017-06-30"
      }
    },
    "IncreaseDecreaseInOtherOperatingCapitalNet": {
      "taxonomy": "us-gaap",
      "label": "Increase (Decrease) in Other Operating Assets and Liabilities, Net",
      "description": "Amount of increase (decrease) in operating assets after deduction of operating liabilities classified as other.",
      "available_units": [
        "USD"
      ],
      "data_points_count": 142,
      "latest_value": {
        "value": 4611000000,
        "date": "2024-12-31",
        "fiscal_year": 2024,
        "form": "10-K",
        "filed": "2025-02-25",
        "unit": "USD",
        "type": "annual"
      },
      "date_range": {
        "earliest": "2007-12-31",
        "latest": "2025-06-30"
      }
    },
    "IntangibleAssetsNetExcludingGoodwill": {
      "taxonomy": "us-gaap",
      "label": "Intangible Assets, Net (Excluding Goodwill)",
      "description": "Sum of the carrying amounts of all intangible assets, excluding goodwill, as of the balance sheet date, net of accumulated amortization and impairment charges.",
      "available_units": [
        "USD"
      ],
      "data_points_count": 8,
      "latest_value": {
        "value": 640000000,
        "date": "2009-12-31",
        "fiscal_year": 2009,
        "form": "10-K",
        "filed": "2010-02-26",
        "unit": "USD",
        "type": "annual"
      },
      "date_range": {
        "earliest": "2008-12-31",
        "latest": "2010-03-31"
      }
    },
    "LeaseAndRentalExpense": {
      "taxonomy": "us-gaap",
      "label": "Operating Leases, Rent Expense",
      "description": "Amount of rent expense incurred for leased assets, including but not limited to, furniture and equipment, that is not directly or indirectly associated with the manufacture, sale or creation of a product or product line.",
      "available_units": [
        "USD"
      ],
      "data_points_count": 30,
      "latest_value": {
        "value": 235000000,
        "date": "2018-12-31",
        "fiscal_year": 2018,
        "form": "10-K",
        "filed": "2019-02-26",
        "unit": "USD",
        "type": "annual"
      },
      "date_range": {
        "earliest": "2008-12-31",
        "latest": "2018-12-31"
      }
    },
    "Liabilities": {
      "taxonomy": "us-gaap",
      "label": "Liabilities",
      "description": "Sum of the carrying amounts as of the balance sheet date of all liabilities that are recognized. Liabilities are probable future sacrifices of economic benefits arising from present obligations of an entity to transfer assets or provide services to other entities in the future.",
      "available_units": [
        "USD"
      ],
      "data_points_count": 134,
      "latest_value": {
        "value": 467497000000,
        "date": "2024-12-31",
        "fiscal_year": 2024,
        "form": "10-K",
        "filed": "2025-02-25",
        "unit": "USD",
        "type": "annual"
      },
      "date_range": {
        "earliest": "2008-12-31",
        "latest": "2025-06-30"
      }
    },
    "NoninterestIncome": {
      "taxonomy": "us-gaap",
      "label": "Noninterest Income",
      "description": "The total amount of noninterest income which may be derived from: (1) fees and commissions; (2) premiums earned; (3) insurance policy charges; (4) the sale or disposal of assets; and (5) other sources not otherwise specified.",
      "available_units": [
        "USD"
      ],
      "data_points_count": 218,
      "latest_value": {
        "value": -813000000,
        "date": "2024-12-31",
        "fiscal_year": 2024,
        "form": "10-K",
        "filed": "2025-02-25",
        "unit": "USD",
        "type": "annual"
      },
      "date_range": {
        "earliest": "2007-12-31",
        "latest": "2025-06-30"
      }
    },
    "OccupancyNet": {
      "taxonomy": "us-gaap",
      "label": "Occupancy, Net",
      "description": "Amount of net occupancy expense that may include items, such as depreciation of facilities and equipment, lease expenses, property taxes and property and casualty insurance expense.",
      "available_units": [
        "USD"
      ],
      "data_points_count": 218,
      "latest_value": {
        "value": 656000000,
        "date": "2024-12-31",
        "fiscal_year": 2024,
        "form": "10-K",
        "filed": "2025-02-25",
        "unit": "USD",
        "type": "annual"
      },
      "date_range": {
        "earliest": "2007-12-31",
        "latest": "2025-06-30"
      }
    },
    "OperatingLeaseRightOfUseAsset": {
      "taxonomy": "us-gaap",
      "label": "Operating Lease, Right-of-Use Asset",
      "description": "Amount of lessee's right to use underlying asset under operating lease.",
      "available_units": [
        "USD"
      ],
      "data_points_count": 46,
      "latest_value": {
        "value": 1015000000,
        "date": "2024-12-31",
        "fiscal_year": 2024,
        "form": "10-K",
        "filed": "2025-02-25",
        "unit": "USD",
        "type": "annual"
      },
      "date_range": {
        "earliest": "2019-03-31",
        "latest": "2025-06-30"
      }
    },
    "OtherAssets": {
      "taxonomy": "us-gaap",
      "label": "Other Assets",
      "description": "Amount of assets classified as other.",
      "available_units": [
        "USD"
      ],
      "data_points_count": 134,
      "latest_value": {
        "value": 37132000000,
        "date": "2024-12-31",
        "fiscal_year": 2024,
        "form": "10-K",
        "filed": "2025-02-25",
        "unit": "USD",
        "type": "annual"
      },
      "date_range": {
        "earliest": "2008-12-31",
        "latest": "2025-06-30"
      }
    },
    "OtherAssetsFairValueDisclosure": {
      "taxonomy": "us-gaap",
      "label": "Other Assets, Fair Value Disclosure",
      "description": "Fair value portion of other assets.",
      "available_units": [
        "USD"
      ],
      "data_points_count": 48,
      "latest_value": {
        "value": 1271000000,
        "date": "2024-12-31",
        "fiscal_year": 2024,
        "form": "10-K",
        "filed": "2025-02-25",
        "unit": "USD",
        "type": "annual"
      },
      "date_range": {
        "earliest": "2018-12-31",
        "latest": "2025-06-30"
      }
    },
    "OtherComprehensiveIncomeDefinedBenefitPlansNetUnamortizedGainLossArisingDuringPeriodBeforeTax": {
      "taxonomy": "us-gaap",
      "label": "Other Comprehensive Income (Loss), Pension and Other Postretirement Benefit Plans, Net Unamortized Gain (Loss) Arising During Period, before Tax (Deprecated 2012-01-31)",
      "description": "Pretax change in the value of either the benefit obligation or the plan assets resulting from experience different from that assumed or from a change in an actuarial assumption, or the consequence of a decision to temporarily deviate from the substantive plan, that has not been recognized in net periodic benefit cost.",
      "available_units": [
        "USD"
      ],
      "data_points_count": 9,
      "latest_value": {
        "value": 270000000,
        "date": "2012-12-31",
        "fiscal_year": 2012,
        "form": "10-K",
        "filed": "2013-03-01",
        "unit": "USD",
        "type": "annual"
      },
      "date_range": {
        "earliest": "2008-12-31",
        "latest": "2012-12-31"
      }
    },
    "PropertyPlantAndEquipmentGross": {
      "taxonomy": "us-gaap",
      "label": "Property, Plant and Equipment, Gross",
      "description": "Amount before accumulated depreciation, depletion and amortization of physical assets used in the normal conduct of business and not intended for resale. Examples include, but are not limited to, land, buildings, machinery and equipment, office equipment, and furniture and fixtures.",
      "available_units": [
        "USD"
      ],
      "data_points_count": 34,
      "latest_value": {
        "value": 5869000000,
        "date": "2024-12-31",
        "fiscal_year": 2024,
        "form": "10-K",
        "filed": "2025-02-25",
        "unit": "USD",
        "type": "annual"
      },
      "date_range": {
        "earliest": "2009-12-31",
        "latest": "2024-12-31"
      }
    },
    "PropertyPlantAndEquipmentNet": {
      "taxonomy": "us-gaap",
      "label": "Property, Plant and Equipment, Net",
      "description": "Amount after accumulated depreciation, depletion and amortization of physical assets used in the normal conduct of business to produce goods and services and not intended for resale. Examples include, but are not limited to, land, buildings, machinery and equipment, office equipment, and furniture and fixtures.",
      "available_units": [
        "USD"
      ],
      "data_points_count": 134,
      "latest_value": {
        "value": 3225000000,
        "date": "2024-12-31",
        "fiscal_year": 2024,
        "form": "10-K",
        "filed": "2025-02-25",
        "unit": "USD",
        "type": "annual"
      },
      "date_range": {
        "earliest": "2008-12-31",
        "latest": "2025-06-30"
      }
    },
    "RentalIncomeNonoperating": {
      "taxonomy": "us-gaap",
      "label": "Rental Income, Nonoperating",
      "description": "Income earned by providing the use of assets to an outside party in exchange for a payment or series of payments that is nonoperating in nature.",
      "available_units": [
        "USD"
      ],
      "data_points_count": 30,
      "latest_value": {
        "value": 20000000,
        "date": "2018-12-31",
        "fiscal_year": 2018,
        "form": "10-K",
        "filed": "2019-02-26",
        "unit": "USD",
        "type": "annual"
      },
      "date_range": {
        "earliest": "2008-12-31",
        "latest": "2018-12-31"
      }
    },
    "RestructuringCharges": {
      "taxonomy": "us-gaap",
      "label": "Restructuring Charges",
      "description": "Amount of expenses associated with exit or disposal activities pursuant to an authorized plan. Excludes expenses related to a discontinued operation or an asset retirement obligation.",
      "available_units": [
        "USD"
      ],
      "data_points_count": 217,
      "latest_value": {
        "value": 120000000,
        "date": "2024-12-31",
        "fiscal_year": 2024,
        "form": "10-K",
        "filed": "2025-02-25",
        "unit": "USD",
        "type": "annual"
      },
      "date_range": {
        "earliest": "2007-12-31",
        "latest": "2025-06-30"
      }
    },
    "ServicingAsset": {
      "taxonomy": "us-gaap",
      "label": "Servicing Asset",
      "description": "Aggregate amount of servicing assets that are subsequently measured at fair value and servicing assets that are subsequently measured using the amortization method.",
      "available_units": [
        "USD"
      ],
      "data_points_count": 10,
      "latest_value": {
        "value": 2023000000,
        "date": "2020-12-31",
        "fiscal_year": 2020,
        "form": "10-K",
        "filed": "2021-02-24",
        "unit": "USD",
        "type": "annual"
      },
      "date_range": {
        "earliest": "2018-12-31",
        "latest": "2020-12-31"
      }
    },
    "ServicingAssetAtAmortizedValue": {
      "taxonomy": "us-gaap",
      "label": "Servicing Asset at Amortized Cost",
      "description": "Amortized amount of contract to service financial assets under which the benefits of servicing are expected to more than adequately compensate the servicer.",
      "available_units": [
        "USD"
      ],
      "data_points_count": 18,
      "latest_value": {
        "value": 107000000,
        "date": "2011-12-31",
        "fiscal_year": 2011,
        "form": "10-K",
        "filed": "2012-02-27",
        "unit": "USD",
        "type": "annual"
      },
      "date_range": {
        "earliest": "2007-12-31",
        "latest": "2011-12-31"
      }
    },
    "ServicingAssetAtAmortizedValueAdditions": {
      "taxonomy": "us-gaap",
      "label": "Servicing Asset at Amortized Cost, Additions",
      "description": "Amount of additions from purchases, assumption or transfer to contract to service financial assets under which the benefits of servicing are expected to more than adequately compensate the servicer.",
      "available_units": [
        "USD"
      ],
      "data_points_count": 9,
      "latest_value": {
        "value": 20000000,
        "date": "2010-12-31",
        "fiscal_year": 2010,
        "form": "10-K",
        "filed": "2011-02-25",
        "unit": "USD",
        "type": "annual"
      },
      "date_range": {
        "earliest": "2008-12-31",
        "latest": "2011-09-30"
      }
    },
    "ServicingAssetAtAmortizedValueAmortization": {
      "taxonomy": "us-gaap",
      "label": "Servicing Asset at Amortized Value, Amortization (Deprecated 2012-01-31)",
      "description": "Decreases in the value of servicing assets due to the periodic amortization in proportion to and over the period of estimated net servicing income.",
      "available_units": [
        "USD"
      ],
      "data_points_count": 9,
      "latest_value": {
        "value": 18000000,
        "date": "2010-12-31",
        "fiscal_year": 2010,
        "form": "10-K",
        "filed": "2011-02-25",
        "unit": "USD",
        "type": "annual"
      },
      "date_range": {
        "earliest": "2008-12-31",
        "latest": "2011-09-30"
      }
    },
    "ServicingAssetAtFairValueAdditions": {
      "taxonomy": "us-gaap",
      "label": "Servicing Asset at Fair Value, Additions",
      "description": "The value of new servicing assets, subsequently measured at fair value, acquired or created during the current period through purchases or from transfers of financial assets.",
      "available_units": [
        "USD"
      ],
      "data_points_count": 48,
      "latest_value": {
        "value": 156000000,
        "date": "2015-12-31",
        "fiscal_year": 2015,
        "form": "10-K",
        "filed": "2016-02-25",
        "unit": "USD",
        "type": "annual"
      },
      "date_range": {
        "earliest": "2008-12-31",
        "latest": "2015-12-31"
      }
    },
    "ServicingAssetAtFairValueAmount": {
      "taxonomy": "us-gaap",
      "label": "Servicing Asset at Fair Value, Amount",
      "description": "Fair value of an asset representing net future revenue from contractually specified servicing fees, late charges, and other ancillary revenues, in excess of future costs related to servicing arrangements.",
      "available_units": [
        "USD"
      ],
      "data_points_count": 176,
      "latest_value": {
        "value": 3708000000,
        "date": "2024-12-31",
        "fiscal_year": 2024,
        "form": "10-K",
        "filed": "2025-02-25",
        "unit": "USD",
        "type": "annual"
      },
      "date_range": {
        "earliest": "2007-12-31",
        "latest": "2025-06-30"
      }
    },
    "ServicingAssetAtFairValueChangesInFairValueResultingFromChangesInValuationInputsOrChangesInAssumptions": {
      "taxonomy": "us-gaap",
      "label": "Servicing Asset at Fair Value, Changes in Fair Value Resulting from Changes in Valuation Inputs or Changes in Assumptions",
      "description": "Amount of increase (decrease) in fair value from changes in the inputs, assumptions, or model used to calculate the fair value of the contract to service financial assets under which the benefits of servicing are expected to more than adequately compensate the servicer.",
      "available_units": [
        "USD"
      ],
      "data_points_count": 30,
      "latest_value": {
        "value": -341000000,
        "date": "2011-12-31",
        "fiscal_year": 2011,
        "form": "10-K",
        "filed": "2012-02-27",
        "unit": "USD",
        "type": "annual"
      },
      "date_range": {
        "earliest": "2008-12-31",
        "latest": "2012-09-30"
      }
    },
    "ServicingAssetAtFairValueOtherChangesInFairValue": {
      "taxonomy": "us-gaap",
      "label": "Servicing Asset at Fair Value, Other Changes in Fair Value",
      "description": "Amount of increase (decrease) from changes in fair value classified as other for a contract to service financial assets under which the benefits of servicing are expected to more than adequately compensate the servicer.",
      "available_units": [
        "USD"
      ],
      "data_points_count": 60,
      "latest_value": {
        "value": -134000000,
        "date": "2015-12-31",
        "fiscal_year": 2015,
        "form": "10-K",
        "filed": "2016-02-25",
        "unit": "USD",
        "type": "annual"
      },
      "date_range": {
        "earliest": "2008-12-31",
        "latest": "2015-12-31"
      }
    },
    "UnrecognizedTaxBenefitsIncomeTaxPenaltiesAccrued": {
      "taxonomy": "us-gaap",
      "label": "Unrecognized Tax Benefits, Income Tax Penalties Accrued",
      "description": "Amount of statutory penalties accrued for a tax position claimed or expected to be claimed by the entity, in its tax return.",
      "available_units": [
        "USD"
      ],
      "data_points_count": 1,
      "latest_value": {
        "value": 1000000,
        "date": "2019-12-31",
        "fiscal_year": 2019,
        "form": "10-K",
        "filed": "2020-03-03",
        "unit": "USD",
        "type": "annual"
      },
      "date_range": {
        "earliest": "2019-12-31",
        "latest": "2019-12-31"
      }
    },
    "UnrecognizedTaxBenefitsInterestOnIncomeTaxesAccrued": {
      "taxonomy": "us-gaap",
      "label": "Unrecognized Tax Benefits, Interest on Income Taxes Accrued",
      "description": "Amount of interest expense accrued for an underpayment of income taxes.",
      "available_units": [
        "USD"
      ],
      "data_points_count": 16,
      "latest_value": {
        "value": 13000000,
        "date": "2024-12-31",
        "fiscal_year": 2024,
        "form": "10-K",
        "filed": "2025-02-25",
        "unit": "USD",
        "type": "annual"
      },
      "date_range": {
        "earliest": "2009-12-31",
        "latest": "2024-12-31"
      }
    },
    "DefinedBenefitPlanFairValueOfPlanAssetsPeriodIncreaseDecrease": {
      "taxonomy": "us-gaap",
      "label": "Defined Benefit Plan, Plan Assets, Period Increase (Decrease)",
      "description": "Amount of increase (decrease) in plan assets of defined benefit plan.",
      "available_units": [
        "USD"
      ],
      "data_points_count": 1,
      "latest_value": {
        "value": -508000000,
        "date": "2024-05-06",
        "fiscal_year": 2024,
        "fiscal_period": "Q2",
        "form": "10-Q",
        "filed": "2024-08-08",
        "unit": "USD",
        "type": "quarterly"
      },
      "date_range": {
        "earliest": "2024-05-06",
        "latest": "2024-05-06"
      }
    },
    "DefinedBenefitPlanActualReturnOnPlanAssets": {
      "taxonomy": "us-gaap",
      "label": "Defined Benefit Plan, Plan Assets, Increase (Decrease) for Actual Return (Loss)",
      "description": "Amount of increase (decrease) in plan assets of defined benefit plan from actual return (loss) determined by change in fair value of plan assets adjusted for contributions, benefit payments, and other expenses.",
      "available_units": [
        "USD"
      ],
      "data_points_count": 2,
      "latest_value": {
        "value": -508000000,
        "date": "2024-05-06",
        "fiscal_year": 2024,
        "form": "10-K",
        "filed": "2025-02-25",
        "unit": "USD",
        "type": "annual"
      },
      "date_range": {
        "earliest": "2024-05-06",
        "latest": "2024-05-06"
      }
    }
  }
}